{".class": "MypyFile", "_fullname": "pytermgui.widgets.interactive", "is_partial_stub_package": false, "is_stub": false, "names": {".class": "SymbolTable", "Button": {".class": "SymbolTableNode", "cross_ref": "pytermgui.widgets.interactive.button.Button", "kind": "Gdef"}, "Checkbox": {".class": "SymbolTableNode", "cross_ref": "pytermgui.widgets.interactive.checkbox.Checkbox", "kind": "Gdef"}, "InputField": {".class": "SymbolTableNode", "cross_ref": "pytermgui.widgets.interactive.input_field.InputField", "kind": "Gdef"}, "KeyboardButton": {".class": "SymbolTableNode", "cross_ref": "pytermgui.widgets.interactive.keyboard_button.KeyboardButton", "kind": "Gdef"}, "Slider": {".class": "SymbolTableNode", "cross_ref": "pytermgui.widgets.interactive.slider.Slider", "kind": "Gdef"}, "Toggle": {".class": "SymbolTableNode", "cross_ref": "pytermgui.widgets.interactive.toggle.Toggle", "kind": "Gdef"}, "__doc__": {".class": "SymbolTableNode", "kind": "Gdef", "node": {".class": "Var", "flags": ["is_ready"], "fullname": "pytermgui.widgets.interactive.__doc__", "name": "__doc__", "type": "builtins.str"}}, "__file__": {".class": "SymbolTableNode", "kind": "Gdef", "node": {".class": "Var", "flags": ["is_ready"], "fullname": "pytermgui.widgets.interactive.__file__", "name": "__file__", "type": "builtins.str"}}, "__name__": {".class": "SymbolTableNode", "kind": "Gdef", "node": {".class": "Var", "flags": ["is_ready"], "fullname": "pytermgui.widgets.interactive.__name__", "name": "__name__", "type": "builtins.str"}}, "__package__": {".class": "SymbolTableNode", "kind": "Gdef", "node": {".class": "Var", "flags": ["is_ready"], "fullname": "pytermgui.widgets.interactive.__package__", "name": "__package__", "type": "builtins.str"}}, "__path__": {".class": "SymbolTableNode", "kind": "Gdef", "node": {".class": "Var", "flags": ["is_ready"], "fullname": "pytermgui.widgets.interactive.__path__", "name": "__path__", "type": {".class": "Instance", "args": ["builtins.str"], "type_ref": "builtins.list"}}}}, "path": "/Users/lapis/Code/Projects/pytermgui/pytermgui/widgets/interactive/__init__.py"}